nonebot_plugin_mcping/__init__.py
nonebot_plugin_mcping/bg.png
nonebot_plugin_mcping/data_source.py
nonebot_plugin_mcping/simhei.ttf
nonebot_plugin_mcping-0.0.9.dist-info/LICENSE
nonebot_plugin_mcping-0.0.9.dist-info/METADATA
nonebot_plugin_mcping-0.0.9.dist-info/WHEEL
nonebot_plugin_mcping-0.0.9.dist-info/RECORD
