Metadata-Version: 2.1
Name: nonebot-plugin-mcping
Version: 0.0.9
Summary: 基于NoneBot的查询MineCraft服务器Motd并返回图片的插件
License: MIT
Author: 17TheWord
Author-email: 17theword@gmail.com
Requires-Python: >=3.10,<4.0
Classifier: License :: OSI Approved :: MIT License
Classifier: Programming Language :: Python :: 3
Classifier: Programming Language :: Python :: 3.10
Classifier: Programming Language :: Python :: 3.11
Classifier: Programming Language :: Python :: 3.12
Requires-Dist: mcstatus (>=11.1.1,<12.0.0)
Requires-Dist: nonebot-adapter-onebot (>=2.4.4,<3.0.0)
Requires-Dist: nonebot-adapter-qq (>=1.5.1,<2.0.0)
Requires-Dist: nonebot-plugin-guild-patch-remix (>=0.2.4,<0.3.0)
Requires-Dist: nonebot2 (>=2.3.3,<3.0.0)
Requires-Dist: pillow (>=10.4.0,<11.0.0)
